sphinxcontrib/autodoc_pydantic/__init__.py
sphinxcontrib/autodoc_pydantic/application.py
sphinxcontrib/autodoc_pydantic/css/autodoc_pydantic.css
sphinxcontrib/autodoc_pydantic/directives/__init__.py
sphinxcontrib/autodoc_pydantic/directives/autodocumenters.py
sphinxcontrib/autodoc_pydantic/directives/directives.py
sphinxcontrib/autodoc_pydantic/directives/options/__init__.py
sphinxcontrib/autodoc_pydantic/directives/options/composites.py
sphinxcontrib/autodoc_pydantic/directives/options/definition.py
sphinxcontrib/autodoc_pydantic/directives/options/enums.py
sphinxcontrib/autodoc_pydantic/directives/options/validators.py
sphinxcontrib/autodoc_pydantic/directives/templates.py
sphinxcontrib/autodoc_pydantic/directives/utility.py
sphinxcontrib/autodoc_pydantic/events.py
sphinxcontrib/autodoc_pydantic/inspection.py
sphinxcontrib/autodoc_pydantic/utility.py
autodoc_pydantic-2.2.0.dist-info/LICENSE
autodoc_pydantic-2.2.0.dist-info/METADATA
autodoc_pydantic-2.2.0.dist-info/WHEEL
autodoc_pydantic-2.2.0.dist-info/RECORD
