Metadata-Version: 2.1
Name: autodoc_pydantic
Version: 2.2.0
Summary: Seamlessly integrate pydantic models in your Sphinx documentation.
Home-page: https://github.com/mansenfranzen/autodoc_pydantic
License: MIT
Keywords: sphinx,pydantic,autodoc,documentation,extension
Author: mansenfranzen
Author-email: franz.woellert@gmail.com
Requires-Python: >=3.8.1,<4.0.0
Classifier: Framework :: Pydantic
Classifier: Framework :: Pydantic :: 2
Classifier: Framework :: Sphinx :: Extension
Classifier: License :: OSI Approved :: MIT License
Classifier: Programming Language :: Python :: 3
Classifier: Programming Language :: Python :: 3.9
Classifier: Programming Language :: Python :: 3.10
Classifier: Programming Language :: Python :: 3.11
Classifier: Programming Language :: Python :: 3.12
Classifier: Topic :: Documentation :: Sphinx
Classifier: Topic :: Software Development :: Documentation
Provides-Extra: docs
Provides-Extra: erdantic
Provides-Extra: linting
Provides-Extra: security
Provides-Extra: test
Provides-Extra: type-checking
Requires-Dist: Sphinx (>=4.0)
Requires-Dist: coverage (>=7,<8) ; extra == "test"
Requires-Dist: defusedxml (>=0.7.1) ; extra == "test"
Requires-Dist: erdantic (<2.0) ; extra == "erdantic"
Requires-Dist: importlib-metadata (>1) ; python_version <= "3.8"
Requires-Dist: mypy (>=1.9,<2.0) ; extra == "type-checking"
Requires-Dist: myst-parser (>=3.0.0,<4.0.0) ; extra == "docs"
Requires-Dist: pip-audit (>=2.7.2,<3.0.0) ; extra == "security"
Requires-Dist: pydantic (>=2.0,<3.0.0)
Requires-Dist: pydantic-settings (>=2.0,<3.0.0)
Requires-Dist: pytest (>=8.0.0,<9.0.0) ; extra == "test"
Requires-Dist: pytest-sugar (>=1.0.0,<2.0.0) ; extra == "test"
Requires-Dist: ruff (>=0.4.0,<0.5.0) ; extra == "linting"
Requires-Dist: sphinx-copybutton (>=0.5.0,<0.6.0) ; extra == "docs"
Requires-Dist: sphinx-rtd-theme (>=2.0.0,<3.0.0) ; extra == "docs"
Requires-Dist: sphinx-tabs (>=3,<4) ; extra == "docs"
Requires-Dist: sphinxcontrib-mermaid (>=0.9.0,<0.10.0) ; extra == "docs"
Requires-Dist: types-docutils (>=0.20,<0.21) ; extra == "type-checking"
Requires-Dist: typing-extensions (>=4.11,<5.0) ; (python_version <= "3.9") and (extra == "type-checking")
Project-URL: Documentation, https://github.com/mansenfranzen/autodoc_pydantic
Project-URL: Repository, https://github.com/mansenfranzen/autodoc_pydantic
